traversaal/SemanticSearch.py
traversaal/__init__.py
traversaal/test.py
traversaal-0.6982.dist-info/LICENSE.txt
traversaal-0.6982.dist-info/METADATA
traversaal-0.6982.dist-info/WHEEL
traversaal-0.6982.dist-info/top_level.txt
traversaal-0.6982.dist-info/RECORD
