Metadata-Version: 2.1
Name: traversaal
Version: 0.6982
Summary: A semantic search package for hotel data
Home-page: https://github.com/hamzafarooq
Author: Traversaal
Author-email: hello@traversaal.com
License: Apache License 2.0
Keywords: Transformer Networks BERT XLNet sentence embedding PyTorch NLP deep learning
Classifier: Development Status :: 5 - Production/Stable
Classifier: Intended Audience :: Science/Research
Classifier: License :: OSI Approved :: Apache Software License
Classifier: Programming Language :: Python :: 3.6
Classifier: Topic :: Scientific/Engineering :: Artificial Intelligence
Requires-Python: >=3.6.0
License-File: LICENSE.txt
Requires-Dist: transformers (<5.0.0,>=4.6.0)
Requires-Dist: tqdm
Requires-Dist: torch (>=1.6.0)
Requires-Dist: torchvision
Requires-Dist: numpy
Requires-Dist: scikit-learn
Requires-Dist: scipy
Requires-Dist: nltk
Requires-Dist: sentencepiece
Requires-Dist: huggingface-hub (>=0.4.0)
